xseed-max-box-creation/__init__.py
xseed-max-box-creation/buildInstall.py
xseed-max-box-creation/changeUser.py
xseed-max-box-creation/configureMasterBox.py
xseed-max-box-creation/dockerComposeEnvVariable.py
xseed-max-box-creation/graphQL.py
xseed-max-box-creation/installCommonPackagesTools.py
xseed-max-box-creation/lockAppsOnLauncher.py
xseed-max-box-creation/masterBoxCreation.py
xseed-max-box-creation/packageCleanUp.py
xseed-max-box-creation/prerequisiteChecks.py
xseed-max-box-creation/xseedmodules/__init__.py
xseed-max-box-creation/xseedmodules/buildInstall.py
xseed-max-box-creation/xseedmodules/changeUser.py
xseed-max-box-creation/xseedmodules/configureMasterBox.py
xseed-max-box-creation/xseedmodules/dockerComposeEnvVariable.py
xseed-max-box-creation/xseedmodules/graphQL.py
xseed-max-box-creation/xseedmodules/installCommonPackagesTools.py
xseed-max-box-creation/xseedmodules/lockAppsOnLauncher.py
xseed-max-box-creation/xseedmodules/packageCleanUp.py
xseed-max-box-creation/xseedmodules/prerequisiteChecks.py
xseed_max_box_creation/__init__.py
xseed_max_box_creation/xseedmodules/__init__.py
xseed_max_box_creation/xseedmodules/buildInstall.py
xseed_max_box_creation/xseedmodules/changeUser.py
xseed_max_box_creation/xseedmodules/configureMasterBox.py
xseed_max_box_creation/xseedmodules/dockerComposeEnvVariable.py
xseed_max_box_creation/xseedmodules/graphQL.py
xseed_max_box_creation/xseedmodules/installCommonPackagesTools.py
xseed_max_box_creation/xseedmodules/lockAppsOnLauncher.py
xseed_max_box_creation/xseedmodules/packageCleanUp.py
xseed_max_box_creation/xseedmodules/prerequisiteChecks.py
xseed_minicampus_creation/__init__.py
xseed_minicampus_creation/xseedmodules/__init__.py
xseed_minicampus_creation/xseedmodules/buildInstall.py
xseed_minicampus_creation/xseedmodules/changeUser.py
xseed_minicampus_creation/xseedmodules/configureMasterBox.py
xseed_minicampus_creation/xseedmodules/dockerComposeEnvVariable.py
xseed_minicampus_creation/xseedmodules/graphQL.py
xseed_minicampus_creation-0.1.dist-info/METADATA
xseed_minicampus_creation-0.1.dist-info/WHEEL
xseed_minicampus_creation-0.1.dist-info/top_level.txt
xseed_minicampus_creation-0.1.dist-info/RECORD
