Metadata-Version: 2.1
Name: xseed-minicampus-creation
Version: 0.1
Summary: Max box installation package
Home-page: UNKNOWN
Author: Mayank Jain
Author-email: Mayank.jain@xseededucation.com
License: UNKNOWN
Platform: UNKNOWN
Classifier: Programming Language :: Python :: 3
Classifier: License :: OSI Approved :: MIT License
Classifier: Operating System :: OS Independent
